egm/__init__.py
egm/egm.py
egm-1.1.5.dist-info/LICENSE
egm-1.1.5.dist-info/METADATA
egm-1.1.5.dist-info/WHEEL
egm-1.1.5.dist-info/top_level.txt
egm-1.1.5.dist-info/RECORD
