Metadata-Version: 2.1
Name: egm
Version: 1.1.5
Summary: A python package for plotting Evidence Gap Maps using Plotly
Home-page: https://https://github.com/mb7419/egm/
Author: Mohit Bhatnagar
Author-email: mohit@uplytics.com
License: UNKNOWN
Keywords: Plotly,evidence gap map,bubble graphs,interactive graphs
Platform: UNKNOWN
Requires-Dist: plotly
Requires-Dist: pandas
